ShenghuoHeike/README.md
ShenghuoHeike/__init__.py
ShenghuoHeike/__main__.py
ShenghuoHeike/file.epub
ShenghuoHeike/index.html
ShenghuoHeike/css/__init__.py
ShenghuoHeike/css/annotations.css
ShenghuoHeike/css/main.css
ShenghuoHeike/css/normalize.css
ShenghuoHeike/css/popup.css
ShenghuoHeike/font/__init__.py
ShenghuoHeike/font/fontello.eot
ShenghuoHeike/font/fontello.svg
ShenghuoHeike/font/fontello.ttf
ShenghuoHeike/font/fontello.woff
ShenghuoHeike/img/__init__.py
ShenghuoHeike/img/annotator-glyph-sprite.png
ShenghuoHeike/img/annotator-icon-sprite.png
ShenghuoHeike/img/apple-touch-icon.png
ShenghuoHeike/img/cancelfullscreen.png
ShenghuoHeike/img/close.png
ShenghuoHeike/img/fullscreen.png
ShenghuoHeike/img/loader.gif
ShenghuoHeike/img/menu-icon.png
ShenghuoHeike/img/save.png
ShenghuoHeike/img/saved.png
ShenghuoHeike/img/settings-s.png
ShenghuoHeike/img/settings.png
ShenghuoHeike/img/star.png
ShenghuoHeike/js/__init__.py
ShenghuoHeike/js/epub.js
ShenghuoHeike/js/epub.min.js
ShenghuoHeike/js/epub.min.map
ShenghuoHeike/js/hooks.min.js
ShenghuoHeike/js/hooks.min.map
ShenghuoHeike/js/reader.js
ShenghuoHeike/js/reader.js.map
ShenghuoHeike/js/reader.min.js
ShenghuoHeike/js/reader.min.map
ShenghuoHeike/js/hooks/__init__.py
ShenghuoHeike/js/hooks/extensions/__init__.py
ShenghuoHeike/js/hooks/extensions/highlight.js
ShenghuoHeike/js/libs/__init__.py
ShenghuoHeike/js/libs/jquery.min.js
ShenghuoHeike/js/libs/localforage.min.js
ShenghuoHeike/js/libs/screenfull.js
ShenghuoHeike/js/libs/screenfull.min.js
ShenghuoHeike/js/libs/zip.min.js
ShenghuoHeike/js/plugins/__init__.py
ShenghuoHeike/js/plugins/hypothesis.js
ShenghuoHeike/js/plugins/search.js
shenghuo_heike-2022.10.15.0.dist-info/METADATA
shenghuo_heike-2022.10.15.0.dist-info/WHEEL
shenghuo_heike-2022.10.15.0.dist-info/entry_points.txt
shenghuo_heike-2022.10.15.0.dist-info/top_level.txt
shenghuo_heike-2022.10.15.0.dist-info/RECORD
